yaml_arg_configer/__init__.py
yaml_arg_configer/yaml_argparser.py
yaml_arg_configer/yaml_loader.py
yaml_arg_configer-0.1.1.dist-info/LICENSE
yaml_arg_configer-0.1.1.dist-info/METADATA
yaml_arg_configer-0.1.1.dist-info/WHEEL
yaml_arg_configer-0.1.1.dist-info/top_level.txt
yaml_arg_configer-0.1.1.dist-info/RECORD
