Metadata-Version: 2.2
Name: yaml_arg_configer
Version: 0.1.1
Summary: Simplifies the process of parsing command-line arguments and configurations from YAML files
Home-page: https://github.com/eiPI1-0/yaml_arg_configer
Author: eipi10
Author-email: yorosikunano@gmail.com
Classifier: Programming Language :: Python :: 3
Classifier: License :: OSI Approved :: MIT License
Classifier: Operating System :: OS Independent
Requires-Python: >=3.8
License-File: LICENSE
Requires-Dist: pyyaml
